rmm/__init__.py
rmm/__main__.py
rmm/cli.py
rmm/config.py
rmm/exception.py
rmm/manager.py
rmm/mod.py
rmm/modlist.py
rmm/modsconfig.py
rmm/multiselect.py
rmm/path.py
rmm/steam.py
rmm/util.py
rmm2-1.3.0.dist-info/METADATA
rmm2-1.3.0.dist-info/WHEEL
rmm2-1.3.0.dist-info/entry_points.txt
rmm2-1.3.0.dist-info/licenses/LICENSE
rmm2-1.3.0.dist-info/RECORD
