Metadata-Version: 2.4
Name: rmm2
Version: 1.3.0
Summary: A RimWorld Mod Manager (forked from rmm-spoons)
Project-URL: Homepage, https://github.com/duong-dt/rmm2
Project-URL: Repository, https://github.com/duong-dt/rmm2
Author: Duong, Michael Ciociola
Maintainer-email: Duong <dotungduong2@gmail.com>
License-Expression: GPL-3.0-only
License-File: LICENSE
Classifier: License :: OSI Approved :: GNU Affero General Public License v3
Classifier: Operating System :: OS Independent
Classifier: Programming Language :: Python :: 3
Classifier: Topic :: Games/Entertainment
Classifier: Topic :: System :: Archiving :: Packaging
Requires-Python: <4.0,>3.8
Requires-Dist: beautifulsoup4<5,>=4.12.2
Requires-Dist: networkx~=3.1
Requires-Dist: tabulate<0.10,>=0.9.0
